{
  "data": [
    {
      "id": 1,
      "key": "work",
      "name": "Work Experiences",
      "list": [
        {
          "id": 0,
          "company": "Schoenberger Germany Enterprises GmbH & Co. KG",
          "url": "",
          "title": "Frontend Developer",
          "department": "",
          "time_start": "01.2017",
          "time_end": "07.2019",
          "location": "Hohenschäftlarn",
          "description": "test"
        },
        {
          "id": 1,
          "company": "Bosten Consulting Group (BCG)",
          "url": "",
          "title": "Working Student",
          "department": "Technology Advantage",
          "time_start": "",
          "time_end": "",
          "location": "",
          "description": ""
        },
        {
          "id": 2,
          "company": "KPMG Germany",
          "url": "",
          "title": "Technology Engineer",
          "department": "Client Engineer",
          "time_start": "10.2021",
          "time_end": "ongoing",
          "location": "Germany",
          "description": ""
        },
        {
          "id": 3,
          "company": "IBM Germany",
          "url": "",
          "title": "Technology Engineer",
          "department": "Client Engineer",
          "time_start": "10.2021",
          "time_end": "ongoing",
          "location": "Germany",
          "description": ""
        }
      ]
    },
    {
      "id": 2,
      "key": "volunteer",
      "name": "Volunteering Experiences",
      "list": [
        {
          "id": 0,
          "company": "",
          "title": "",
          "department": "",
          "time_start": "",
          "time_end": "",
          "location": "",
          "description": ""
        },
        {
          "id": 1,
          "company": "",
          "title": "",
          "department": "",
          "time_start": "",
          "time_end": "",
          "location": "",
          "description": ""
        }
      ]
    },
    {
      "id": 3,
      "key": "education",
      "name": "Education",
      "list": [
        {
          "id": 0,
          "company": "",
          "title": "",
          "department": "",
          "time_start": "",
          "time_end": "",
          "location": "",
          "description": ""
        },
        {
          "id": 0,
          "company": "",
          "title": "",
          "department": "",
          "time_start": "",
          "time_end": "",
          "location": "",
          "description": ""
        },
        {
          "id": 0,
          "company": "",
          "title": "",
          "department": "",
          "time_start": "",
          "time_end": "",
          "location": "",
          "description": ""
        }
      ]
    }
  ]
}
